{
  "ret": "0",
  "msg": "操作成功",
  "data": {
    "goods_id": "70",
    "goods_name": "【德国直邮】Aptamil爱他美3段奶粉 800g 婴儿配方（10-12月适用）6罐发货",
    "goods_thumb": "http://s06.lmbang.com/M00/AE/A9/DpgiA1U17mWAAw3eAAH5CuR7F9E757.jpg!c300x300x100.jpg",
    "goods_sub_name": "【包裹用Bpost经德国发出  从比利时布鲁塞尔机场起飞】\n德国本土超市或药妆店直采，严选德国本土公司合作，空运至中国，从奶粉来源、包装、发货环节保障安全、准确的快递到家。 请务必填写真实姓名，下单后5个工作日发货，不适合急买！每单限购6罐，可与限6罐购买的800g规格德国爱他美混搭购买。每买一单请更换收货人、地址、电话。请注意提前囤货。如出现质量问题或奶粉外漏，我们将全额退款并补偿。\n如被税，凭借被税图片证明，返等值辣豆！\n【特别提示】订单提交后，非商品质量问题，概不退换！敬请谅解！",
    "cat_id": "527",
    "market_price": "345",
    "shop_price": "209",
    "goods_brief": "【包裹用Bpost经德国发出  从比利时布鲁塞尔机场起飞】\n德国本土超市或药妆店直采，严选德国本土公司合作，空运至中国，从奶粉来源、包装、发货环节保障安全、准确的快递到家。 请务必填写真实姓名，下单后5个工作日发货，不适合急买！每单限购6罐，可与限6罐购买的800g规格德国爱他美混搭购买。每买一单请更换收货人、地址、电话。请注意提前囤货。如出现质量问题或奶粉外漏，我们将全额退款并补偿。\n如被税，凭借被税图片证明，返等值辣豆！\n【特别提示】订单提交后，非商品质量问题，概不退换！敬请谅解！",
    "goods_desc": "<p class=\"MsoNormal\" style=\"background:white;text-align:left;\" align=\"left\">\n\t<span style=\"line-height:1.5;\"> \n\t<table style=\"width:100%;\" border=\"1\" bordercolor=\"#000000\" cellpadding=\"2\" cellspacing=\"0\">\n\t\t<tbody>\n\t\t\t<tr>\n\t\t\t\t<td>\n\t\t\t\t\t<span style=\"font-size:18px;\">品名</span><br />\n\t\t\t\t</td>\n\t\t\t\t<td>\n\t\t\t\t\t<b><span style=\"font-size:18px;\">Aptamil爱他美婴儿配方奶粉</span><span style=\"font-size:18px;\"> 3</span><span style=\"font-size:18px;\">段</span></b><br />\n\t\t\t\t</td>\n\t\t\t</tr>\n\t\t\t<tr>\n\t\t\t\t<td>\n\t\t\t\t\t<span style=\"font-size:18px;\">产地</span><br />\n\t\t\t\t</td>\n\t\t\t\t<td>\n\t\t\t\t\t<span style=\"font-size:18px;\">德国</span><br />\n\t\t\t\t</td>\n\t\t\t</tr>\n\t\t\t<tr>\n\t\t\t\t<td>\n\t\t\t\t\t<span style=\"font-size:18px;\">品牌</span><br />\n\t\t\t\t</td>\n\t\t\t\t<td>\n\t\t\t\t\t<b><span style=\"font-size:18px;\">Aptamil</span></b><br />\n\t\t\t\t</td>\n\t\t\t</tr>\n\t\t\t<tr>\n\t\t\t\t<td>\n\t\t\t\t\t<span style=\"font-size:18px;\">适用阶段</span><br />\n\t\t\t\t</td>\n\t\t\t\t<td>\n\t\t\t\t\t<span style=\"font-size:18px;\">3段</span><br />\n\t\t\t\t</td>\n\t\t\t</tr>\n\t\t\t<tr>\n\t\t\t\t<td>\n\t\t\t\t\t<span style=\"font-size:18px;\">适用年龄</span><br />\n\t\t\t\t</td>\n\t\t\t\t<td>\n\t\t\t\t\t<span style=\"font-size:18px;\">10-12个月</span><br />\n\t\t\t\t</td>\n\t\t\t</tr>\n\t\t\t<tr>\n\t\t\t\t<td>\n\t\t\t\t\t<span style=\"font-size:18px;\">规格重量</span><br />\n\t\t\t\t</td>\n\t\t\t\t<td>\n\t\t\t\t\t<span style=\"font-size:18px;\">800g</span><br />\n\t\t\t\t</td>\n\t\t\t</tr>\n\t\t\t<tr>\n\t\t\t\t<td>\n\t\t\t\t\t<span style=\"font-size:18px;\">保质期</span><br />\n\t\t\t\t</td>\n\t\t\t\t<td>\n\t\t\t\t\t<span style=\"font-size:18px;\">18个月</span><br />\n\t\t\t\t</td>\n\t\t\t</tr>\n\t\t\t<tr>\n\t\t\t\t<td>\n\t\t\t\t\t<span style=\"font-size:18px;\">包装种类</span><br />\n\t\t\t\t</td>\n\t\t\t\t<td>\n\t\t\t\t\t<span style=\"font-size:18px;\">环保纸质</span><br />\n\t\t\t\t</td>\n\t\t\t</tr>\n\t\t\t<tr>\n\t\t\t\t<td>\n\t\t\t\t\t<span style=\"font-size:18px;\">储藏方法</span><br />\n\t\t\t\t</td>\n\t\t\t\t<td>\n\t\t\t\t\t<span style=\"font-size:18px;\">避光阴凉</span><br />\n\t\t\t\t</td>\n\t\t\t</tr>\n\t\t</tbody>\n\t</table>\n</span> \n</p>\n<p class=\"MsoNormal\" style=\"margin-left:21pt;\">\n\t <span style=\"font-size:14pt;font-family:宋体;color:black;\">为什么选择德国<span>Aptamil</span>爱他美？<span></span></span> \n</p>\n<p class=\"MsoNormal\" style=\"margin-left:21pt;\">\n\t<span style=\"font-family:宋体;color:black;\"><span style=\"font-size:18px;\">六大理由：</span><span></span></span> \n</p>\n<p class=\"MsoNormal\" style=\"margin-left:21pt;\">\n\t<span style=\"font-family:宋体;color:black;\"><span style=\"font-size:18px;\">第一：德国奶粉有最严格的监管制度。</span><span></span></span> \n</p>\n<p class=\"MsoNormal\" style=\"margin-left:21pt;\">\n\t<span style=\"font-size:18px;font-family:宋体;color:black;\"><span style=\"font-size:18px;\">    </span></span><span style=\"font-family:宋体;color:black;\"><span style=\"font-size:18px;\">德国规定，婴儿配方奶粉以属于药品管制，所有的奶粉上架前都是要经过可以等同于药品的检测程序的检验</span><span></span></span> \n</p>\n<p class=\"MsoNormal\" style=\"margin-left:21pt;\">\n\t<span style=\"font-family:宋体;color:black;\"><span style=\"font-size:18px;\">第二：所有婴幼儿配方奶粉均采用电子标签芯片全程管理。</span><span></span></span> \n</p>\n<p class=\"MsoNormal\" style=\"margin-left:21pt;\">\n\t<span style=\"font-size:18px;font-family:宋体;color:black;\"><span style=\"font-size:18px;\">    </span></span><span style=\"font-family:宋体;color:black;\"><span style=\"font-size:18px;\">通过每罐奶粉的芯片，可准确了解该罐奶粉的产地、牧场、工厂、生产线、生产时间等信息，有效地保证了食品安全。</span><span></span></span> \n</p>\n<p class=\"MsoNormal\" style=\"margin-left:21pt;\">\n\t<span style=\"font-size:18px;font-family:宋体;color:black;\">第三：德国严苛的质量认证体系和德国人认真严谨的做事风格铸就了风靡全球的“Made in Germany”。</span><span style=\"font-size:18px;\"> </span> \n</p>\n<p class=\"MsoNormal\" style=\"margin-left:21pt;\">\n\t<span style=\"font-family:宋体;color:black;\"><span style=\"font-size:18px;\">第四：德国爱他美配方奶粉近似母乳。</span><span></span></span> \n</p>\n<p class=\"MsoNormal\" style=\"margin-left:21pt;\">\n\t<span style=\"font-size:18px;font-family:宋体;color:black;\"><span style=\"font-size:18px;\">    </span></span><span style=\"font-family:宋体;color:black;\"><span style=\"font-size:18px;\">乳清蛋白与酪蛋白比例与母乳完全一致，采用天然牧场的奶源，不含抗生素，特别有助与婴幼儿消化吸收，不上火。</span><span></span></span> \n</p>\n<p class=\"MsoNormal\" style=\"margin-left:21pt;\">\n\t<span style=\"font-family:宋体;color:black;\"><span style=\"font-size:18px;\">第五：含</span><span style=\"font-size:18px;\">DHA</span><span style=\"font-size:18px;\">及</span><span style=\"font-size:18px;\">AA</span><span style=\"font-size:18px;\">，添加铁质，不含蔗糖，含有健康益菌因子菊糖。</span><span></span></span> \n</p>\n<p class=\"MsoNormal\" style=\"margin-left:21pt;\">\n\t<span style=\"font-size:18px;font-family:宋体;color:black;\"><span style=\"font-size:18px;\">    </span></span><span style=\"font-family:宋体;color:black;\"><span style=\"font-size:18px;\">爱他美全力出击</span><span style=\"font-size:18px;\">,</span><span style=\"font-size:18px;\">改善婴幼儿免疫力</span><span style=\"font-size:18px;\">,</span><span style=\"font-size:18px;\">在奶粉中添加了益生菌成长的营养成分</span><span style=\"font-size:18px;\">,</span><span style=\"font-size:18px;\">帮助孩子健康成长。</span><span></span></span> \n</p>\n<p class=\"MsoNormal\" style=\"margin-left:21pt;\">\n\t<span style=\"font-family:宋体;color:black;\"><span style=\"font-size:18px;\">第六：提供丰富氨基酸组合。</span><span></span></span> \n</p>\n<p class=\"MsoNormal\" style=\"margin-left:21pt;text-indent:21pt;\">\n\t<span style=\"font-family:宋体;color:black;\"><span style=\"font-size:18px;\">其中富含色氨酸和半胱氨酸</span><span style=\"font-size:18px;\">,</span><span style=\"font-size:18px;\">转化为</span><span style=\"font-size:18px;\">5-</span><span style=\"font-size:18px;\">羟色胺和牛磺酸</span><span style=\"font-size:18px;\">,</span><span style=\"font-size:18px;\">帮助促进记忆力和注意力等多顶中枢神经功能发育。</span><span></span></span> \n</p>\n<p class=\"MsoNormal\" style=\"margin-left:21pt;\">\n\t<b><span></span></b> \n</p>\n<p class=\"MsoNormal\" style=\"margin-left:21pt;\">\n\t<b><span style=\"font-size:18px;\">Q1:</span></b><b><span style=\"font-size:18px;font-family:宋体;\">问这次购买的奶粉包装为什么和之前不一样？</span></b><b><span></span></b> \n</p>\n<p class=\"MsoNormal\" style=\"margin-left:21pt;\">\n\t<b><span style=\"font-size:18px;\">A</span></b><b><span style=\"font-size:18px;font-family:宋体;\">：</span></b><span style=\"font-size:18px;\">Aptamil</span><span style=\"font-size:18px;font-family:宋体;\">爱他美公司经常会根据需要对奶粉进行细微调整，随时的调整，我们会告知妈妈们，请妈妈们以一颗平常心对待奶粉包装调整问题。</span><span></span> \n</p>\n<p class=\"MsoNormal\" style=\"margin-left:21pt;\">\n\t<span></span> \n</p>\n<p class=\"MsoNormal\" style=\"margin-left:21pt;\">\n\t<b><span style=\"font-size:18px;\">Q2</span></b><b><span style=\"font-size:18px;font-family:宋体;\">：奶粉开罐后容易结块？</span></b><b><span></span></b> \n</p>\n<p class=\"MsoNormal\" style=\"margin-left:21pt;\">\n\t<b><span style=\"font-size:18px;\">A</span></b><b><span style=\"font-size:18px;font-family:宋体;\">：</span></b><span style=\"font-size:18px;font-family:宋体;\">奶粉可能是假性结块，也就是在运输过程中的剧烈晃动，奶粉颗粒由于静电作用而吸附在一起。妈妈们可以用干净的勺子轻轻挑，结块会自行散开。奶粉开罐后放在阴凉通风处，请在一个月内食用，在奶粉罐外套一个密封袋，更好保存奶粉，防止潮湿而结块。</span><span></span> \n</p>\n<p class=\"MsoNormal\" style=\"margin-left:21pt;\">\n\t<span></span> \n</p>\n<p class=\"MsoNormal\" style=\"margin-left:21pt;\">\n\t<b><span style=\"font-size:18px;\">Q3</span></b><b><span style=\"font-size:18px;font-family:宋体;\">：收到奶粉憋罐、小扣子掉了是否要紧？</span></b><b><span></span></b> \n</p>\n<p class=\"MsoNormal\" style=\"margin-left:21pt;\">\n\t<b><span style=\"font-size:18px;\">A</span></b><b><span style=\"font-size:18px;font-family:宋体;\">：</span></b><span style=\"font-size:18px;font-family:宋体;\">国外奶粉包装都是环保包装，由于长途运输，部分奶粉出现憋罐，安全扣脱落情况，这些现象无法</span><span style=\"font-size:18px;\">100%</span><span style=\"font-size:18px;font-family:宋体;\">避免，这些不属于质量问题，请各位妈妈多给环保包装一些宽容。</span><span></span> \n</p>\n<p class=\"MsoNormal\" style=\"margin-left:21pt;\">\n\t<span></span> \n</p>\n<p class=\"MsoNormal\" style=\"margin-left:21pt;\">\n\t<b><span style=\"font-size:18px;\">Q4</span></b><b><span style=\"font-size:18px;font-family:宋体;\">：英国爱他美和德国爱他美哪个更好</span></b><b><span style=\"font-size:18px;\"> / </span></b><b><span style=\"font-size:18px;font-family:宋体;\">英国爱他美和德国爱他美的区别？</span></b><b><span></span></b> \n</p>\n<p class=\"MsoNormal\" style=\"margin-left:21pt;\">\n\t<b><span style=\"font-size:18px;\">A</span></b><b><span style=\"font-size:18px;font-family:宋体;\">：</span></b><span style=\"font-size:18px;font-family:宋体;\">在奶源方面，英国爱他美的奶源来自于爱尔兰牧场，德国的奶源是瑞士的，奶源决定了奶粉的品质，这两个奶粉地都很好，有口皆碑。在配方上两个爱他美大同小异，英国版的添加了麦芽糊精成分，这样让奶粉更利于溶解。在价格方面，由于英国政府对宝宝食品有补贴，英国版市价低一些。</span> \n</p>\n<p class=\"MsoNormal\" style=\"margin-left:21pt;\">\n\t<span style=\"font-size:18px;font-family:宋体;\"><img src=\"http://s05.lmbang.com/M00/88/5F/DhFprFQ43NSACtxFAAGE1RxthoE314.jpg!q100\" alt=\"\" /><img src=\"http://s06.lmbang.com/M00/88/5F/DhFprFQ43NWADX8FAAMZb0LoGek290.jpg!q100\" alt=\"\" /><img src=\"http://s04.lmbang.com/M00/88/5F/DhFprFQ43NaAUwfzAAHdaJ0lQ8E390.jpg!q100\" alt=\"\" /><img src=\"http://s08.lmbang.com/M00/88/5F/DhFprFQ43NiACSO_AAJRb7-S_6U924.jpg!q100\" alt=\"\" /><img src=\"http://s04.lmbang.com/M00/76/A3/eQ519FQ43NiAWTsuAAIIiRElmrs145.jpg!q100\" alt=\"\" /><img src=\"http://s08.lmbang.com/M00/88/5F/DhFprFQ43NmAJ2vuAAIOEAaeKpg656.jpg!q100\" alt=\"\" /><img src=\"http://s06.lmbang.com/M00/88/5F/DhFprFQ43NmATmMTAAHGszv7WoI908.jpg!q100\" alt=\"\" /><img src=\"http://s03.lmbang.com/M00/76/A3/eQ519FQ43NqAIIWWAAHsxaK7T_o053.jpg!q100\" alt=\"\" /><img src=\"http://s08.lmbang.com/M00/88/5F/DhFprFQ43NuAQ57zAAPfrTIur2I950.jpg!q100\" alt=\"\" /><img src=\"http://s07.lmbang.com/M00/76/A3/eQ519FQ43NyADekHAAMrl3tEpa4101.jpg!q100\" alt=\"\" /><img src=\"http://s08.lmbang.com/M00/88/5F/DhFprFQ43N2ATE4uAAOdkHFxRnk640.jpg!q100\" alt=\"\" /><img src=\"http://s06.lmbang.com/M00/76/A3/eQ519FQ43N6AATo4AAMsiY9O0-4950.jpg!q100\" alt=\"\" /><img src=\"http://s06.lmbang.com/M00/88/5F/DhFprFQ43N6ADw7RAAONa5La1v0419.jpg!q100\" alt=\"\" /><img src=\"http://s08.lmbang.com/M00/88/5F/DhFprFQ43OCANss6AANqdeMoNNU574.jpg!q100\" alt=\"\" /><img src=\"http://s05.lmbang.com/M00/92/66/DhFprFRApnCAZPsaAAJyGRqgxNQ080.jpg!q100\" alt=\"\" /><img src=\"http://s06.lmbang.com/M00/76/A3/eQ519FQ43O2AHifNAAMcAXBDtB8686.jpg!q100\" alt=\"\" /><img src=\"http://s04.lmbang.com/M00/76/A3/eQ519FQ43O2AVc8hAALSKjBkcjY709.jpg!q100\" alt=\"\" /><img src=\"http://s04.lmbang.com/M00/76/A3/eQ519FQ43O-AcyYPAAJXIqmF1zM182.jpg!q100\" alt=\"\" /><img src=\"http://s05.lmbang.com/M00/76/A3/eQ519FQ43PCAXAIcAAJLm0eBkI0426.jpg!q100\" alt=\"\" /><img src=\"http://s03.lmbang.com/M00/88/5F/DhFprFQ43PGAQtXrAAMk45eWVjQ661.jpg!q100\" alt=\"\" /><img src=\"http://s04.lmbang.com/M00/88/5F/DhFprFQ43PKAbGo-AALv-vGtb8s273.jpg!q100\" alt=\"\" /><br />\n</span> \n</p>\n<p class=\"MsoNormal\" style=\"margin-left:21pt;\">\n\t<br />\n</p>",
    "is_shipping": "免邮费",
    "is_on_sale": "1",
    "is_alone_sale": "1",
    "is_delete": "0",
    "adapt_age": "0",
    "sold_number": 1772,
    "comment_number": "62",
    "evaluation": "5",
    "haito_country": "http://s01.lmbang.com/M00/1A/90/DhFprFPtvkqAdOkOAAALYYadx_M750.png",
    "limit_number": "6",
    "brand_id": "29",
    "buy_limit_num": "0",
    "goods_unit": "罐",
    "haito_country_type": "4",
    "promote_price": "209.00",
    "promote_start_date": "1440381600",
    "promote_end_date": "1463112000",
    "sell_type": "1",
    "ship_template_id": "8",
    "keywords": "Aptamil，德国爱他美，爱他美，3段",
    "is_seckill": "0",
    "business_type": "3",
    "unsale_time": "1430878494",
    "create_time": "1429597800",
    "goods_sn": "16221408",
    "purchase_area": "18",
    "store_id": "0",
    "platform": "1",
    "haito_id": "12",
    "template_id": "8",
    "cat_name": "德国爱他美",
    "is_duty": "0",
    "distribution": "http://s07.lmbang.com/M00/4E/D6/DhFprFQOriWAORqJAAQy45IiH2g231.png!c640x200x100.png",
    "parameters": [
      {
        "goods_attr_id": "63591",
        "goods_id": "70",
        "cat_id": "527",
        "attr_key": "产地",
        "attr_value": "德国",
        "attr_name": ""
      },
      {
        "goods_attr_id": "741",
        "goods_id": "70",
        "cat_id": "0",
        "attr_key": "shiyongnianling",
        "attr_value": "10-12个月",
        "attr_name": "适用年龄"
      },
      {
        "goods_attr_id": "742",
        "goods_id": "70",
        "cat_id": "0",
        "attr_key": "duanshu",
        "attr_value": "3段",
        "attr_name": "段数"
      },
      {
        "goods_attr_id": "743",
        "goods_id": "70",
        "cat_id": "0",
        "attr_key": "chandi",
        "attr_value": "德国",
        "attr_name": "产地"
      },
      {
        "goods_attr_id": "744",
        "goods_id": "70",
        "cat_id": "0",
        "attr_key": "guige",
        "attr_value": "800g",
        "attr_name": "规格"
      },
      {
        "attr_value": "16221408",
        "attr_name": "商品编码"
      },
      {
        "attr_value": "Aptamil /爱他美",
        "attr_name": "品牌"
      }
    ],
    "attribute": {
      "value": [
        {
          "default_attr_id": "3749",
          "attr_name": "属性",
          "attr_id": "1513",
          "attr_value_list": [
            {
              "attr_value_id": "3749",
              "attr_value": "3段"
            }
          ]
        },
        {
          "default_attr_id": "3745",
          "attr_name": "规格",
          "attr_id": "1358",
          "attr_value_list": [
            {
              "attr_value_id": "3745",
              "attr_value": "罐"
            }
          ]
        }
      ],
      "combin": [
        {
          "link_ids": "3749|3745",
          "product_number": 99,
          "mod_number": 99,
          "p_id": 11450,
          "shop_price": "209.00",
          "market_price": "345.00",
          "discount": "6.1"
        }
      ],
      "product_number": 99,
      "mod_number": 99,
      "shop_price": "209.00",
      "market_price": "345.00",
      "p_id": 11450,
      "discount": "6.1"
    },
    "promote": {
      "promote_price": "209.00",
      "discount": "6.1",
      "endtime": "1463112000"
    },
    "goods_warrants": {
      "tips": [
        "http://s02.lmbang.com/M00/C9/EB/DpgiA1VQXMuAJFVNAAAGt9j7PvA170.png",
        "http://s02.lmbang.com/M00/C9/EB/DpgiA1VQXM-AcMprAAAHHH3wfcY881.png",
        "http://s08.lmbang.com/M00/DE/BC/DpgiA1VmhF6AV5XIAAAGyHFaKbs034.png",
        "http://s08.lmbang.com/M00/C9/EB/DpgiA1VQXM-AJeiMAAAHFn96EqM886.png"
      ],
      "url": ""
    },
    "pictures": [
      {
        "picture": "http://s06.lmbang.com/M00/2B/7F/eQ519FQEO6iAfEewAAIiEZSB2ww313.jpg",
        "thumb": "http://s06.lmbang.com/M00/2B/7F/eQ519FQEO6iAfEewAAIiEZSB2ww313.jpg!c640x640x100.jpg"
      },
      {
        "picture": "http://s05.lmbang.com/M00/3D/2E/DhFprFQEO6mAKGDFAAIYcKriWq8210.jpg",
        "thumb": "http://s05.lmbang.com/M00/3D/2E/DhFprFQEO6mAKGDFAAIYcKriWq8210.jpg!c640x640x100.jpg"
      },
      {
        "picture": "http://s08.lmbang.com/M00/3D/2E/DhFprFQEO6mAOGVMAAIJWjapOXA698.jpg",
        "thumb": "http://s08.lmbang.com/M00/3D/2E/DhFprFQEO6mAOGVMAAIJWjapOXA698.jpg!c640x640x100.jpg"
      },
      {
        "picture": "http://s08.lmbang.com/M00/2B/7F/eQ519FQEO6mAB65sAAIQvGvWPD8546.jpg",
        "thumb": "http://s08.lmbang.com/M00/2B/7F/eQ519FQEO6mAB65sAAIQvGvWPD8546.jpg!c640x640x100.jpg"
      },
      {
        "picture": "http://s05.lmbang.com/M00/2B/7F/eQ519FQEO6qAW6m1AAIXblniEYM587.jpg",
        "thumb": "http://s05.lmbang.com/M00/2B/7F/eQ519FQEO6qAW6m1AAIXblniEYM587.jpg!c640x640x100.jpg"
      },
      {
        "picture": "http://s03.lmbang.com/M00/3D/2E/DhFprFQEO6uAHMGtAAIvhjjUPHc271.jpg",
        "thumb": "http://s03.lmbang.com/M00/3D/2E/DhFprFQEO6uAHMGtAAIvhjjUPHc271.jpg!c640x640x100.jpg"
      }
    ],
    "goods_extend": {
      "business_type": "3",
      "tips": "服务： 由品牌供应商从德国(保)发货"
    }
  },
  "timestamp": 1482720184
}