{
  "ret": "0",
  "msg": "操作成功",
  "data": {
    "list": [
      {
        "spec_id": "13506",
        "spec_name": "LAMBKIN圣诞特卖",
        "banner": "http://s08.lmbang.com/M00/0E/5D/ecloA1haGVGAIEwVAAHyYekwv0A415.jpg",
        "start_time": "1482372000",
        "end_time": "1482631199",
        "hits": "608",
        "remind_num": "2",
        "discount": "1.5",
        "typeid": "0",
        "ad_link": "",
        "sold_total_nums": "14098",
        "sortnum": 1016,
        "notice": "剩1天",
        "is_remind": "0",
        "is_start": "1"
      },
      {
        "spec_id": "13426",
        "spec_name": "熊北鼻双旦特卖",
        "banner": "http://s03.lmbang.com/M00/05/C3/ecloD1hQtNyAY47wAAG-OwdSwxE704.jpg",
        "start_time": "1482458400",
        "end_time": "1482940799",
        "hits": "12",
        "remind_num": "0",
        "discount": "1.3",
        "typeid": "0",
        "ad_link": "",
        "sold_total_nums": "470",
        "sortnum": 1014,
        "notice": "剩5天",
        "is_remind": "0",
        "is_start": "1"
      },
      {
        "spec_id": "13465",
        "spec_name": "源自韩国 爱恩幼孕期护肤 双旦美孕趴",
        "banner": "http://s02.lmbang.com/M00/27/14/DpgiA1hXhlaAeX9QAAIWEhuAPa0509.jpg",
        "start_time": "1482458400",
        "end_time": "1482940799",
        "hits": "16",
        "remind_num": "1",
        "discount": "1.8",
        "typeid": "0",
        "ad_link": "",
        "sold_total_nums": "12013",
        "sortnum": 1014,
        "notice": "剩5天",
        "is_remind": "0",
        "is_start": "1"
      },
      {
        "spec_id": "13466",
        "spec_name": "双旦专场满199减30",
        "banner": "http://s05.lmbang.com/M00/27/1A/DpgiA1hXlaqAWn0VAANo-mZKCLk170.jpg",
        "start_time": "1482458400",
        "end_time": "1482940799",
        "hits": "14",
        "remind_num": "0",
        "discount": "2.4",
        "typeid": "0",
        "ad_link": "",
        "sold_total_nums": "8518",
        "sortnum": 1014,
        "notice": "剩5天",
        "is_remind": "0",
        "is_start": "1"
      },
      {
        "spec_id": "13467",
        "spec_name": "哇爱待产用品双旦专场",
        "banner": "http://s03.lmbang.com/M00/0D/E2/ecloA1hXxFSAfdaNAAO_IgWesUw611.jpg",
        "start_time": "1482458400",
        "end_time": "1482940799",
        "hits": "15",
        "remind_num": "0",
        "discount": "1.7",
        "typeid": "0",
        "ad_link": "",
        "sold_total_nums": "17072",
        "sortnum": 1014,
        "notice": "剩5天",
        "is_remind": "0",
        "is_start": "1"
      },
      {
        "spec_id": "13470",
        "spec_name": "亲润欢购双旦特卖场",
        "banner": "http://s05.lmbang.com/M00/07/5B/ecloD1hYfkqAWQsPAAOgkhTk7hQ811.jpg",
        "start_time": "1482458400",
        "end_time": "1482940799",
        "hits": "22",
        "remind_num": "1",
        "discount": "0.5",
        "typeid": "0",
        "ad_link": "",
        "sold_total_nums": "12275",
        "sortnum": 1014,
        "notice": "剩5天",
        "is_remind": "0",
        "is_start": "1"
      },
      {
        "spec_id": "13475",
        "spec_name": "双旦节促销",
        "banner": "http://s05.lmbang.com/M00/27/42/DpgiA1hYhiiAfsrcAAF16lPy5Is623.jpg",
        "start_time": "1482458400",
        "end_time": "1482940799",
        "hits": "19",
        "remind_num": "0",
        "discount": "1.3",
        "typeid": "0",
        "ad_link": "",
        "sold_total_nums": "23550",
        "sortnum": 1014,
        "notice": "剩5天",
        "is_remind": "0",
        "is_start": "1"
      },
      {
        "spec_id": "13477",
        "spec_name": "奥克欧母婴双旦节专场",
        "banner": "http://s04.lmbang.com/M00/0D/FF/ecloA1hYj1OAQRqtAAGVjNraMGw403.jpg",
        "start_time": "1482458400",
        "end_time": "1482940799",
        "hits": "24",
        "remind_num": "0",
        "discount": "0.5",
        "typeid": "0",
        "ad_link": "",
        "sold_total_nums": "1456",
        "sortnum": 1014,
        "notice": "剩5天",
        "is_remind": "0",
        "is_start": "1"
      },
      {
        "spec_id": "13481",
        "spec_name": "双旦进口尿裤特卖专场",
        "banner": "http://s08.lmbang.com/M00/07/71/ecloD1hYxhmAcoE-AAJ3yasZjAw999.jpg",
        "start_time": "1482458400",
        "end_time": "1482940799",
        "hits": "52",
        "remind_num": "0",
        "discount": "6.1",
        "typeid": "0",
        "ad_link": "",
        "sold_total_nums": "18356",
        "sortnum": 1014,
        "notice": "剩5天",
        "is_remind": "0",
        "is_start": "1"
      },
      {
        "spec_id": "13490",
        "spec_name": "双旦特卖-日本贝亲",
        "banner": "http://s08.lmbang.com/M00/27/57/DpgiA1hYyXSAWkv6AAIyKq84rZA940.jpg",
        "start_time": "1482458400",
        "end_time": "1482940799",
        "hits": "45",
        "remind_num": "0",
        "discount": "2.1",
        "typeid": "0",
        "ad_link": "",
        "sold_total_nums": "59418",
        "sortnum": 1014,
        "notice": "剩5天",
        "is_remind": "0",
        "is_start": "1"
      },
      {
        "spec_id": "13492",
        "spec_name": "布朗博士护肤保湿专场",
        "banner": "http://s05.lmbang.com/M00/27/5C/DpgiA1hY1FKAKzh_AAF2emCTxsk361.jpg",
        "start_time": "1482458400",
        "end_time": "1482940799",
        "hits": "14",
        "remind_num": "0",
        "discount": "2.8",
        "typeid": "0",
        "ad_link": "",
        "sold_total_nums": "12640",
        "sortnum": 1014,
        "notice": "剩5天",
        "is_remind": "0",
        "is_start": "1"
      },
      {
        "spec_id": "13494",
        "spec_name": "双旦-进口卫生巾",
        "banner": "http://s03.lmbang.com/M00/27/6C/DpgiA1hZAxiAIeaPAAJVEm1TH4s432.jpg",
        "start_time": "1482458400",
        "end_time": "1482940799",
        "hits": "16",
        "remind_num": "1",
        "discount": "4.0",
        "typeid": "0",
        "ad_link": "",
        "sold_total_nums": "10568",
        "sortnum": 1014,
        "notice": "剩5天",
        "is_remind": "0",
        "is_start": "1"
      },
      {
        "spec_id": "13524",
        "spec_name": "伊威营养辅食专场特卖",
        "banner": "http://s03.lmbang.com/M00/27/F5/DpgiA1hbkHuAQNPAAAHf2Bvl3AI782.jpg",
        "start_time": "1482458400",
        "end_time": "1482940799",
        "hits": "16",
        "remind_num": "0",
        "discount": "8.6",
        "typeid": "0",
        "ad_link": "",
        "sold_total_nums": "40125",
        "sortnum": 1014,
        "notice": "剩5天",
        "is_remind": "0",
        "is_start": "1"
      },
      {
        "spec_id": "13092",
        "spec_name": "Aptamil /爱他美品牌专场",
        "banner": "http://s02.lmbang.com/M00/FB/A0/ecloD1gkGmCAQnenAANiTQdVFMI244.jpg",
        "start_time": "1482372000",
        "end_time": "1482717600",
        "hits": "1397",
        "remind_num": "1",
        "discount": "5.4",
        "typeid": "0",
        "ad_link": "",
        "sold_total_nums": "49123",
        "sortnum": 1013,
        "notice": "剩2天",
        "is_remind": "0",
        "is_start": "1"
      },
      {
        "spec_id": "13462",
        "spec_name": "纽奇双旦全场特卖",
        "banner": "http://s08.lmbang.com/M00/0E/25/ecloA1hY-rKAaaAWAAGf9MWuaEM201.jpg",
        "start_time": "1482458400",
        "end_time": "1482940799",
        "hits": "31",
        "remind_num": "0",
        "discount": "3.9",
        "typeid": "0",
        "ad_link": "",
        "sold_total_nums": "547",
        "sortnum": 1013,
        "notice": "剩5天",
        "is_remind": "0",
        "is_start": "1"
      },
      {
        "spec_id": "13469",
        "spec_name": "润本双蛋节特惠专场",
        "banner": "http://s08.lmbang.com/M00/07/83/ecloD1hY9myAWuoNAAL2TXst590441.jpg",
        "start_time": "1482458400",
        "end_time": "1482940799",
        "hits": "6",
        "remind_num": "0",
        "discount": "4.0",
        "typeid": "0",
        "ad_link": "",
        "sold_total_nums": "12993",
        "sortnum": 1013,
        "notice": "剩5天",
        "is_remind": "0",
        "is_start": "1"
      },
      {
        "spec_id": "13471",
        "spec_name": "安儿欣双蛋节特惠专场",
        "banner": "http://s08.lmbang.com/M00/0E/24/ecloA1hY-BeAeELRAAMdUx2SoyU676.jpg",
        "start_time": "1482458400",
        "end_time": "1482940799",
        "hits": "24",
        "remind_num": "0",
        "discount": "3.0",
        "typeid": "0",
        "ad_link": "",
        "sold_total_nums": "9230",
        "sortnum": 1013,
        "notice": "剩5天",
        "is_remind": "0",
        "is_start": "1"
      },
      {
        "spec_id": "13472",
        "spec_name": "日康双蛋节特惠专场",
        "banner": "http://s02.lmbang.com/M00/07/83/ecloD1hY9WyAcrvDAANQINGdRMY037.jpg",
        "start_time": "1482458400",
        "end_time": "1482940799",
        "hits": "14",
        "remind_num": "0",
        "discount": "5.2",
        "typeid": "0",
        "ad_link": "",
        "sold_total_nums": "4845",
        "sortnum": 1013,
        "notice": "剩5天",
        "is_remind": "0",
        "is_start": "1"
      },
      {
        "spec_id": "13473",
        "spec_name": "小比咔双蛋节特惠专场",
        "banner": "http://s01.lmbang.com/M00/27/69/DpgiA1hY9euAB5hvAAOaej6zHgg636.jpg",
        "start_time": "1482458400",
        "end_time": "1482940799",
        "hits": "23",
        "remind_num": "0",
        "discount": "5.6",
        "typeid": "0",
        "ad_link": "",
        "sold_total_nums": "5967",
        "sortnum": 1013,
        "notice": "剩5天",
        "is_remind": "0",
        "is_start": "1"
      },
      {
        "spec_id": "13483",
        "spec_name": "3rd年底大促99-22（双旦）",
        "banner": "http://s03.lmbang.com/M00/07/73/ecloD1hYzGeALTipAAQa44-3Omk553.jpg",
        "start_time": "1482458400",
        "end_time": "1482940799",
        "hits": "22",
        "remind_num": "0",
        "discount": "1.5",
        "typeid": "0",
        "ad_link": "",
        "sold_total_nums": "15693",
        "sortnum": 1013,
        "notice": "剩5天",
        "is_remind": "0",
        "is_start": "1"
      },
      {
        "spec_id": "13485",
        "spec_name": "杜蕾斯特卖，满99减20",
        "banner": "http://s05.lmbang.com/M00/0E/16/ecloA1hY1HaAVtMyAAG2GCFl0tg084.png",
        "start_time": "1482458400",
        "end_time": "1482940799",
        "hits": "10",
        "remind_num": "0",
        "discount": "6.0",
        "typeid": "0",
        "ad_link": "",
        "sold_total_nums": "15746",
        "sortnum": 1013,
        "notice": "剩5天",
        "is_remind": "0",
        "is_start": "1"
      },
      {
        "spec_id": "13489",
        "spec_name": "奥贝因塑身衣特卖专场",
        "banner": "http://s04.lmbang.com/M00/07/77/ecloD1hY1niAQuiPAAGBEoF1uNA535.jpg",
        "start_time": "1482458400",
        "end_time": "1482940799",
        "hits": "36",
        "remind_num": "0",
        "discount": "1.5",
        "typeid": "0",
        "ad_link": "",
        "sold_total_nums": "3068",
        "sortnum": 1013,
        "notice": "剩5天",
        "is_remind": "0",
        "is_start": "1"
      },
      {
        "spec_id": "13491",
        "spec_name": "双旦节特卖",
        "banner": "http://s04.lmbang.com/M00/27/67/DpgiA1hY8tSAY5sGAAGmzugpJeE035.jpg",
        "start_time": "1482458400",
        "end_time": "1482940799",
        "hits": "8",
        "remind_num": "0",
        "discount": "2.0",
        "typeid": "0",
        "ad_link": "",
        "sold_total_nums": "2011",
        "sortnum": 1013,
        "notice": "剩5天",
        "is_remind": "0",
        "is_start": "1"
      },
      {
        "spec_id": "13502",
        "spec_name": "双旦年末狂欢节",
        "banner": "http://s07.lmbang.com/M00/0E/5C/ecloA1haFhiAWKZrAAGtWIPVi7A048.jpg",
        "start_time": "1482458400",
        "end_time": "1482940799",
        "hits": "64",
        "remind_num": "0",
        "discount": "1.3",
        "typeid": "0",
        "ad_link": "",
        "sold_total_nums": "8439",
        "sortnum": 1013,
        "notice": "剩5天",
        "is_remind": "0",
        "is_start": "1"
      },
      {
        "spec_id": "13507",
        "spec_name": "德国原装进口喜宝辅食专场特卖",
        "banner": "http://s08.lmbang.com/M00/07/C1/ecloD1haIN-AYLLIAAGu4yStiwg481.jpg",
        "start_time": "1482458400",
        "end_time": "1482890399",
        "hits": "17",
        "remind_num": "0",
        "discount": "6.8",
        "typeid": "0",
        "ad_link": "",
        "sold_total_nums": "2988",
        "sortnum": 1013,
        "notice": "剩4天",
        "is_remind": "0",
        "is_start": "1"
      },
      {
        "spec_id": "13022",
        "spec_name": "Thompson&#039;s/汤普森品牌专场",
        "banner": "http://s02.lmbang.com/M00/19/65/DpgiA1gcQ82AJELzAAFZ_Pwmh4o647.jpg",
        "start_time": "1482458400",
        "end_time": "1482804000",
        "hits": "339",
        "remind_num": "5",
        "discount": "6.5",
        "typeid": "0",
        "ad_link": "",
        "sold_total_nums": "1458",
        "sortnum": 1012,
        "notice": "剩3天",
        "is_remind": "0",
        "is_start": "1"
      },
      {
        "spec_id": "13468",
        "spec_name": "贝贝桃双旦节活动",
        "banner": "http://s07.lmbang.com/M00/0D/FC/ecloA1hYgN6AD8lhAAGhfX4EVuc138.jpg",
        "start_time": "1482458400",
        "end_time": "1482940799",
        "hits": "40",
        "remind_num": "0",
        "discount": "1.0",
        "typeid": "0",
        "ad_link": "",
        "sold_total_nums": "31753",
        "sortnum": 1012,
        "notice": "剩5天",
        "is_remind": "0",
        "is_start": "1"
      },
      {
        "spec_id": "13474",
        "spec_name": "双旦浪漫钜惠",
        "banner": "http://s08.lmbang.com/M00/0E/62/ecloA1haIsuANqvqAAEMobkBFxg116.jpg",
        "start_time": "1482458400",
        "end_time": "1482940799",
        "hits": "12",
        "remind_num": "0",
        "discount": "2.8",
        "typeid": "0",
        "ad_link": "",
        "sold_total_nums": "4556",
        "sortnum": 1012,
        "notice": "剩5天",
        "is_remind": "0",
        "is_start": "1"
      },
      {
        "spec_id": "13476",
        "spec_name": "婧麒双旦节狂欢场",
        "banner": "http://s08.lmbang.com/M00/27/44/DpgiA1hYjeqAFzszAANhr84Y4FU550.jpg",
        "start_time": "1482458400",
        "end_time": "1482940799",
        "hits": "10",
        "remind_num": "0",
        "discount": "1.7",
        "typeid": "0",
        "ad_link": "",
        "sold_total_nums": "4115",
        "sortnum": 1012,
        "notice": "剩5天",
        "is_remind": "0",
        "is_start": "1"
      },
      {
        "spec_id": "13486",
        "spec_name": "Dettol滴露品牌专场，满99减20",
        "banner": "http://s01.lmbang.com/M00/0E/17/ecloA1hY1YGAThdDAAR97XIcwf4841.png",
        "start_time": "1482458400",
        "end_time": "1482940799",
        "hits": "10",
        "remind_num": "0",
        "discount": "5.1",
        "typeid": "0",
        "ad_link": "",
        "sold_total_nums": "8362",
        "sortnum": 1012,
        "notice": "剩5天",
        "is_remind": "0",
        "is_start": "1"
      },
      {
        "spec_id": "13487",
        "spec_name": "Scholl/爽健品牌专场，满99减20",
        "banner": "http://s06.lmbang.com/M00/27/5D/DpgiA1hY1hOANorjAAGeuEiTnmM617.png",
        "start_time": "1482458400",
        "end_time": "1482940799",
        "hits": "7",
        "remind_num": "0",
        "discount": "6.6",
        "typeid": "0",
        "ad_link": "",
        "sold_total_nums": "3854",
        "sortnum": 1012,
        "notice": "剩5天",
        "is_remind": "0",
        "is_start": "1"
      },
      {
        "spec_id": "13488",
        "spec_name": "六甲村孕妈用品年终钜惠",
        "banner": "http://s05.lmbang.com/M00/0E/16/ecloA1hY1CGAYykkAAFqsgQZ4cw102.jpg",
        "start_time": "1482458400",
        "end_time": "1482940799",
        "hits": "14",
        "remind_num": "0",
        "discount": "4.2",
        "typeid": "0",
        "ad_link": "",
        "sold_total_nums": "14860",
        "sortnum": 1012,
        "notice": "剩5天",
        "is_remind": "0",
        "is_start": "1"
      },
      {
        "spec_id": "13496",
        "spec_name": "贝贝怡双旦节特卖专场",
        "banner": "http://s02.lmbang.com/M00/07/86/ecloD1hZAL2AM3dCAAIEp9h-Ghg004.jpg",
        "start_time": "1482458400",
        "end_time": "1482940799",
        "hits": "51",
        "remind_num": "0",
        "discount": "2.8",
        "typeid": "0",
        "ad_link": "",
        "sold_total_nums": "27592",
        "sortnum": 1012,
        "notice": "剩5天",
        "is_remind": "0",
        "is_start": "1"
      },
      {
        "spec_id": "13499",
        "spec_name": "双旦狂欢 好礼送不停",
        "banner": "http://s08.lmbang.com/M00/0E/54/ecloA1hZ-HCARWFoAAFuR2KT2_M417.jpg",
        "start_time": "1482458400",
        "end_time": "1482940799",
        "hits": "4",
        "remind_num": "0",
        "discount": "5.8",
        "typeid": "0",
        "ad_link": "",
        "sold_total_nums": "1940",
        "sortnum": 1012,
        "notice": "剩5天",
        "is_remind": "0",
        "is_start": "1"
      },
      {
        "spec_id": "13509",
        "spec_name": "2017双旦特惠",
        "banner": "http://s05.lmbang.com/M00/07/CD/ecloD1haQg6AdDoDAAMVgn1fKlA047.jpg",
        "start_time": "1482458400",
        "end_time": "1482940799",
        "hits": "19",
        "remind_num": "0",
        "discount": "2.1",
        "typeid": "0",
        "ad_link": "",
        "sold_total_nums": "19886",
        "sortnum": 1012,
        "notice": "剩5天",
        "is_remind": "0",
        "is_start": "1"
      },
      {
        "spec_id": "13514",
        "spec_name": "韩国原装进口艾唯倪专场特卖",
        "banner": "http://s05.lmbang.com/M00/27/EC/DpgiA1hbeIiAB4DFAAG4pC5Y0pY324.jpg",
        "start_time": "1482458400",
        "end_time": "1482940799",
        "hits": "15",
        "remind_num": "0",
        "discount": "8.7",
        "typeid": "0",
        "ad_link": "",
        "sold_total_nums": "3152",
        "sortnum": 1012,
        "notice": "剩5天",
        "is_remind": "0",
        "is_start": "1"
      },
      {
        "spec_id": "13515",
        "spec_name": "布布宝贝纸尿裤大促",
        "banner": "http://s06.lmbang.com/M00/27/ED/DpgiA1hbeoGAG-PRAAMvzSoZb3k177.jpg",
        "start_time": "1482458400",
        "end_time": "1482940799",
        "hits": "8",
        "remind_num": "0",
        "discount": "3.2",
        "typeid": "0",
        "ad_link": "",
        "sold_total_nums": "3726",
        "sortnum": 1012,
        "notice": "剩5天",
        "is_remind": "0",
        "is_start": "1"
      },
      {
        "spec_id": "13449",
        "spec_name": "康宝妈咪双旦特卖专场",
        "banner": "http://s07.lmbang.com/M00/0D/FD/ecloA1hYiJmAfRnyAAGGBrOXa_0760.jpg",
        "start_time": "1482458400",
        "end_time": "1482940799",
        "hits": "38",
        "remind_num": "0",
        "discount": "1.7",
        "typeid": "0",
        "ad_link": "",
        "sold_total_nums": "23260",
        "sortnum": 1011,
        "notice": "剩5天",
        "is_remind": "0",
        "is_start": "1"
      },
      {
        "spec_id": "13450",
        "spec_name": "KALOO 法国品牌安抚宝宝不安的情绪",
        "banner": "http://s06.lmbang.com/M00/07/75/ecloD1hY0GqAYzhLAAGmB6_91Tk197.jpg",
        "start_time": "1482458400",
        "end_time": "1482940799",
        "hits": "17",
        "remind_num": "0",
        "discount": "4.7",
        "typeid": "0",
        "ad_link": "",
        "sold_total_nums": "1448",
        "sortnum": 1011,
        "notice": "剩5天",
        "is_remind": "0",
        "is_start": "1"
      },
      {
        "spec_id": "13453",
        "spec_name": "LUDI 新生儿必备 品牌特卖",
        "banner": "http://s01.lmbang.com/M00/0E/16/ecloA1hY0mqAKUXqAAGzkYx8c2w171.jpg",
        "start_time": "1482458400",
        "end_time": "1482717599",
        "hits": "14",
        "remind_num": "0",
        "discount": "6.0",
        "typeid": "0",
        "ad_link": "",
        "sold_total_nums": "2350",
        "sortnum": 1011,
        "notice": "剩2天",
        "is_remind": "0",
        "is_start": "1"
      },
      {
        "spec_id": "13478",
        "spec_name": "花笙糖双旦特卖活动",
        "banner": "http://s03.lmbang.com/M00/0E/02/ecloA1hYmLmAMWCCAAFeSXxJ7_8436.jpg",
        "start_time": "1482458400",
        "end_time": "1482940799",
        "hits": "17",
        "remind_num": "0",
        "discount": "2.2",
        "typeid": "0",
        "ad_link": "",
        "sold_total_nums": "8258",
        "sortnum": 1011,
        "notice": "剩5天",
        "is_remind": "0",
        "is_start": "1"
      },
      {
        "spec_id": "13479",
        "spec_name": "MOSREM双旦节特卖专场",
        "banner": "http://s07.lmbang.com/M00/27/48/DpgiA1hYmjmAFNMlAAMLtOYIpOY897.jpg",
        "start_time": "1482458400",
        "end_time": "1482940799",
        "hits": "18",
        "remind_num": "0",
        "discount": "0.9",
        "typeid": "0",
        "ad_link": "",
        "sold_total_nums": "4802",
        "sortnum": 1011,
        "notice": "剩5天",
        "is_remind": "0",
        "is_start": "1"
      },
      {
        "spec_id": "13480",
        "spec_name": "笛爱儿诞旦狂欢优惠大派送",
        "banner": "http://s07.lmbang.com/M00/27/4D/DpgiA1hYqiaAZuwyAAG7ELJXam8324.jpg",
        "start_time": "1482458400",
        "end_time": "1482940799",
        "hits": "18",
        "remind_num": "0",
        "discount": "0.5",
        "typeid": "0",
        "ad_link": "",
        "sold_total_nums": "27818",
        "sortnum": 1011,
        "notice": "剩5天",
        "is_remind": "0",
        "is_start": "1"
      },
      {
        "spec_id": "13482",
        "spec_name": "小魔糖双旦特卖狂欢",
        "banner": "http://s05.lmbang.com/M00/07/6A/ecloD1hYsrCAbYjNAAFV50G9NcI457.jpg",
        "start_time": "1482458400",
        "end_time": "1482940799",
        "hits": "8",
        "remind_num": "0",
        "discount": "5.0",
        "typeid": "0",
        "ad_link": "",
        "sold_total_nums": "23834",
        "sortnum": 1011,
        "notice": "剩5天",
        "is_remind": "0",
        "is_start": "1"
      },
      {
        "spec_id": "13484",
        "spec_name": "爱得利特卖专场",
        "banner": "http://s07.lmbang.com/M00/27/5B/DpgiA1hY0T6APHMnAAIJ5l_FIRw826.jpg",
        "start_time": "1482458400",
        "end_time": "1482940799",
        "hits": "13",
        "remind_num": "0",
        "discount": "3.3",
        "typeid": "0",
        "ad_link": "",
        "sold_total_nums": "28217",
        "sortnum": 1011,
        "notice": "剩5天",
        "is_remind": "0",
        "is_start": "1"
      },
      {
        "spec_id": "13497",
        "spec_name": "卡绚QBH双旦特卖活动",
        "banner": "http://s08.lmbang.com/M00/0E/54/ecloA1hZ-YGAZNEzAAJ14oDXdNY251.jpg",
        "start_time": "1482458400",
        "end_time": "1482940799",
        "hits": "16",
        "remind_num": "0",
        "discount": "1.9",
        "typeid": "0",
        "ad_link": "",
        "sold_total_nums": "3210",
        "sortnum": 1011,
        "notice": "剩5天",
        "is_remind": "0",
        "is_start": "1"
      },
      {
        "spec_id": "13504",
        "spec_name": "ZazaBaby座椅双旦特惠",
        "banner": "http://s04.lmbang.com/M00/0E/5E/ecloA1haGm2AGBv5AAF9TyheOyA555.jpg",
        "start_time": "1482458400",
        "end_time": "1482940799",
        "hits": "8",
        "remind_num": "0",
        "discount": "2.5",
        "typeid": "0",
        "ad_link": "",
        "sold_total_nums": "241",
        "sortnum": 1011,
        "notice": "剩5天",
        "is_remind": "0",
        "is_start": "1"
      },
      {
        "spec_id": "13522",
        "spec_name": "运智贝母婴冬日惊喜购",
        "banner": "http://s04.lmbang.com/M00/08/00/ecloD1hbZeyAcXpgAAPShfRiuys547.jpg",
        "start_time": "1482458400",
        "end_time": "1482940799",
        "hits": "7",
        "remind_num": "0",
        "discount": "0.5",
        "typeid": "0",
        "ad_link": "",
        "sold_total_nums": "4260",
        "sortnum": 1011,
        "notice": "剩5天",
        "is_remind": "0",
        "is_start": "1"
      },
      {
        "spec_id": "13169",
        "spec_name": "Aveeno/艾维诺品牌专场",
        "banner": "http://s02.lmbang.com/M00/FD/75/ecloD1gsCg-AL_xuAANWWtxthpA141.jpg",
        "start_time": "1482285600",
        "end_time": "1482631200",
        "hits": "2468",
        "remind_num": "5",
        "discount": "6.2",
        "typeid": "0",
        "ad_link": "",
        "sold_total_nums": "6515",
        "sortnum": 1010,
        "notice": "剩1天",
        "is_remind": "0",
        "is_start": "1"
      },
      {
        "spec_id": "13498",
        "spec_name": "曼娜维QF双旦活动",
        "banner": "http://s06.lmbang.com/M00/07/B4/ecloD1hZ95WAGf8qAAIFkG_r5-Y952.jpg",
        "start_time": "1482458400",
        "end_time": "1482940799",
        "hits": "16",
        "remind_num": "0",
        "discount": "2.2",
        "typeid": "0",
        "ad_link": "",
        "sold_total_nums": "2483",
        "sortnum": 1010,
        "notice": "剩5天",
        "is_remind": "0",
        "is_start": "1"
      },
      {
        "spec_id": "13508",
        "spec_name": "百家好世收纳清洁专场",
        "banner": "http://s02.lmbang.com/M00/07/F9/ecloD1hbTI6Aa61hAAFPvGbr-AM254.jpg",
        "start_time": "1482458400",
        "end_time": "1482940799",
        "hits": "20",
        "remind_num": "0",
        "discount": "1.4",
        "typeid": "0",
        "ad_link": "",
        "sold_total_nums": "3756",
        "sortnum": 1010,
        "notice": "剩5天",
        "is_remind": "0",
        "is_start": "1"
      },
      {
        "spec_id": "13513",
        "spec_name": "小鸡叫叫新年大促",
        "banner": "http://s05.lmbang.com/M00/27/EB/DpgiA1hbdOSAcDgLAAGPuAT9_qo572.jpg",
        "start_time": "1482458400",
        "end_time": "1482940799",
        "hits": "6",
        "remind_num": "0",
        "discount": "3.9",
        "typeid": "0",
        "ad_link": "",
        "sold_total_nums": "35",
        "sortnum": 1010,
        "notice": "剩5天",
        "is_remind": "0",
        "is_start": "1"
      },
      {
        "spec_id": "13516",
        "spec_name": "迪士尼双旦送温暖",
        "banner": "http://s01.lmbang.com/M00/0E/A7/ecloA1hbeWmAYkfNAAL0pXwIKGA750.jpg",
        "start_time": "1482458400",
        "end_time": "1482940799",
        "hits": "11",
        "remind_num": "0",
        "discount": "3.0",
        "typeid": "0",
        "ad_link": "",
        "sold_total_nums": "178",
        "sortnum": 1010,
        "notice": "剩5天",
        "is_remind": "0",
        "is_start": "1"
      },
      {
        "spec_id": "13517",
        "spec_name": "双旦特卖",
        "banner": "http://s04.lmbang.com/M00/27/ED/DpgiA1hbe3eAdPbzAAPHBN6ZDaM479.png",
        "start_time": "1482458400",
        "end_time": "1482890399",
        "hits": "6",
        "remind_num": "0",
        "discount": "6.8",
        "typeid": "0",
        "ad_link": "",
        "sold_total_nums": "3961",
        "sortnum": 1010,
        "notice": "剩4天",
        "is_remind": "0",
        "is_start": "1"
      },
      {
        "spec_id": "13518",
        "spec_name": "双旦狂欢 妈妈聚惠",
        "banner": "http://s01.lmbang.com/M00/0E/A8/ecloA1hbfZuAIMlZAAMovCHZLi0294.jpg",
        "start_time": "1482458400",
        "end_time": "1482940799",
        "hits": "13",
        "remind_num": "0",
        "discount": "3.3",
        "typeid": "0",
        "ad_link": "",
        "sold_total_nums": "2450",
        "sortnum": 1010,
        "notice": "剩5天",
        "is_remind": "0",
        "is_start": "1"
      },
      {
        "spec_id": "13519",
        "spec_name": "布布宝贝宝宝护肤特卖",
        "banner": "http://s01.lmbang.com/M00/0E/A7/ecloA1hbexmAXd48AANBuP7Qv3A661.jpg",
        "start_time": "1482458400",
        "end_time": "1482890399",
        "hits": "6",
        "remind_num": "0",
        "discount": "2.0",
        "typeid": "0",
        "ad_link": "",
        "sold_total_nums": "21271",
        "sortnum": 1010,
        "notice": "剩4天",
        "is_remind": "0",
        "is_start": "1"
      },
      {
        "spec_id": "13520",
        "spec_name": "小米米服饰 温暖整个冬天",
        "banner": "http://s01.lmbang.com/M00/08/07/ecloD1hbe2aATeohAABZeNC8qM8550.jpg",
        "start_time": "1482458400",
        "end_time": "1482940799",
        "hits": "35",
        "remind_num": "0",
        "discount": "5.0",
        "typeid": "0",
        "ad_link": "",
        "sold_total_nums": "88685",
        "sortnum": 1010,
        "notice": "剩5天",
        "is_remind": "0",
        "is_start": "1"
      },
      {
        "spec_id": "13523",
        "spec_name": "日本妮飘强势入驻庆双旦",
        "banner": "http://s07.lmbang.com/M00/0E/AA/ecloA1hbgiWAR9ZNAAPFwdDHQCU757.jpg",
        "start_time": "1482458400",
        "end_time": "1482940799",
        "hits": "13",
        "remind_num": "0",
        "discount": "5.2",
        "typeid": "0",
        "ad_link": "",
        "sold_total_nums": "155",
        "sortnum": 1010,
        "notice": "剩5天",
        "is_remind": "0",
        "is_start": "1"
      },
      {
        "spec_id": "13525",
        "spec_name": "兔本 婴幼儿服饰双旦特卖场",
        "banner": "http://s04.lmbang.com/M00/08/0A/ecloD1hbgVmAR4gHAAFH7Ena1vA676.jpg",
        "start_time": "1482458400",
        "end_time": "1482940799",
        "hits": "13",
        "remind_num": "0",
        "discount": "1.1",
        "typeid": "0",
        "ad_link": "",
        "sold_total_nums": "18825",
        "sortnum": 1010,
        "notice": "剩5天",
        "is_remind": "0",
        "is_start": "1"
      },
      {
        "spec_id": "13526",
        "spec_name": "海恩Heine双旦节狂欢专场",
        "banner": "http://s06.lmbang.com/M00/27/F7/DpgiA1hbl6WAIrxDAASWXIjZuC8826.jpg",
        "start_time": "1482458400",
        "end_time": "1482940799",
        "hits": "13",
        "remind_num": "0",
        "discount": "3.0",
        "typeid": "0",
        "ad_link": "",
        "sold_total_nums": "3624",
        "sortnum": 1010,
        "notice": "剩5天",
        "is_remind": "0",
        "is_start": "1"
      },
      {
        "spec_id": "13069",
        "spec_name": "帕玛氏品牌专场",
        "banner": "http://s02.lmbang.com/M00/1A/AE/DpgiA1ghQu-AV_ouAAF36SFJ8e4503.jpg",
        "start_time": "1482285600",
        "end_time": "1482631200",
        "hits": "1363",
        "remind_num": "4",
        "discount": "4.5",
        "typeid": "0",
        "ad_link": "",
        "sold_total_nums": "2037",
        "sortnum": 1009,
        "notice": "剩1天",
        "is_remind": "0",
        "is_start": "1"
      },
      {
        "spec_id": "13495",
        "spec_name": "日本进口宝宝收纳喂养",
        "banner": "http://s01.lmbang.com/M00/27/6C/DpgiA1hZA8CAZ4J1AAF-RzTi8sc891.jpg",
        "start_time": "1482372000",
        "end_time": "1482631199",
        "hits": "470",
        "remind_num": "1",
        "discount": "2.6",
        "typeid": "0",
        "ad_link": "",
        "sold_total_nums": "22236",
        "sortnum": 1009,
        "notice": "剩1天",
        "is_remind": "0",
        "is_start": "1"
      },
      {
        "spec_id": "13093",
        "spec_name": "ATSUGI/厚木瘦腿袜专场",
        "banner": "http://s06.lmbang.com/M00/02/41/ecloA1gkHG6AKDIUAAOkt90tXO8408.jpg",
        "start_time": "1482372000",
        "end_time": "1482717600",
        "hits": "1941",
        "remind_num": "4",
        "discount": "3.6",
        "typeid": "0",
        "ad_link": "",
        "sold_total_nums": "2409",
        "sortnum": 1008,
        "notice": "剩2天",
        "is_remind": "0",
        "is_start": "1"
      },
      {
        "spec_id": "13099",
        "spec_name": "DHC品牌专场",
        "banner": "http://s07.lmbang.com/M00/FB/A0/ecloD1gkG-aAbLkiAADzCV8yKGM715.jpg",
        "start_time": "1482458400",
        "end_time": "1482804000",
        "hits": "1121",
        "remind_num": "4",
        "discount": "3.9",
        "typeid": "0",
        "ad_link": "",
        "sold_total_nums": "2985",
        "sortnum": 1008,
        "notice": "剩3天",
        "is_remind": "0",
        "is_start": "1"
      },
      {
        "spec_id": "13106",
        "spec_name": "Hipp/喜宝品牌专场",
        "banner": "http://s07.lmbang.com/M00/02/42/ecloA1gkH4uAUgi7AALA1BWlY8k283.jpg",
        "start_time": "1482458400",
        "end_time": "1482804000",
        "hits": "1602",
        "remind_num": "5",
        "discount": "4.7",
        "typeid": "0",
        "ad_link": "",
        "sold_total_nums": "13932",
        "sortnum": 1008,
        "notice": "剩3天",
        "is_remind": "0",
        "is_start": "1"
      },
      {
        "spec_id": "13110",
        "spec_name": "Joie/巧儿宜品牌专场",
        "banner": "http://s06.lmbang.com/M00/02/42/ecloA1gkIL2AB1cGAAI0Po4nvR4779.jpg",
        "start_time": "1482458400",
        "end_time": "1482804000",
        "hits": "3252",
        "remind_num": "8",
        "discount": "3.9",
        "typeid": "0",
        "ad_link": "",
        "sold_total_nums": "241",
        "sortnum": 1008,
        "notice": "剩3天",
        "is_remind": "0",
        "is_start": "1"
      },
      {
        "spec_id": "13074",
        "spec_name": "SANA/莎娜品牌专场",
        "banner": "http://s07.lmbang.com/M00/FA/C9/ecloD1ghQiqAJEfzAAGZloOwpTU852.jpg",
        "start_time": "1482372000",
        "end_time": "1482717600",
        "hits": "982",
        "remind_num": "3",
        "discount": "5.4",
        "typeid": "0",
        "ad_link": "",
        "sold_total_nums": "1673",
        "sortnum": 1007,
        "notice": "剩2天",
        "is_remind": "0",
        "is_start": "1"
      },
      {
        "spec_id": "13095",
        "spec_name": "Red Seal/红印品牌专场",
        "banner": "http://s02.lmbang.com/M00/FB/A0/ecloD1gkGuuAZFeSAADkswtht1k615.jpg",
        "start_time": "1482372000",
        "end_time": "1482717600",
        "hits": "1020",
        "remind_num": "2",
        "discount": "4.4",
        "typeid": "0",
        "ad_link": "",
        "sold_total_nums": "3439",
        "sortnum": 1007,
        "notice": "剩2天",
        "is_remind": "0",
        "is_start": "1"
      },
      {
        "spec_id": "13018",
        "spec_name": "Goat Soap品牌专场",
        "banner": "http://s01.lmbang.com/M00/00/1F/ecloA1gcP_KAH2L2AAD4rXzeD9w198.jpg",
        "start_time": "1482372000",
        "end_time": "1482717600",
        "hits": "545",
        "remind_num": "5",
        "discount": "5.7",
        "typeid": "0",
        "ad_link": "",
        "sold_total_nums": "2113",
        "sortnum": 1006,
        "notice": "剩2天",
        "is_remind": "0",
        "is_start": "1"
      },
      {
        "spec_id": "13459",
        "spec_name": "尤妮佳纸尿裤特卖",
        "banner": "http://s06.lmbang.com/M00/27/00/DpgiA1hXR6yAAKbvAAOIRWWJff4797.jpg",
        "start_time": "1482285600",
        "end_time": "1482631199",
        "hits": "316",
        "remind_num": "1",
        "discount": "5.9",
        "typeid": "0",
        "ad_link": "",
        "sold_total_nums": "5953",
        "sortnum": 1004,
        "notice": "剩1天",
        "is_remind": "0",
        "is_start": "1"
      },
      {
        "spec_id": "12811",
        "spec_name": "Montagne Jeunesse品牌专场",
        "banner": "http://s07.lmbang.com/M00/15/A6/DpgiA1gN6vCAMVlNAAJdoGXbHXY022.jpg",
        "start_time": "1482285600",
        "end_time": "1482631200",
        "hits": "493",
        "remind_num": "4",
        "discount": "7.9",
        "typeid": "0",
        "ad_link": "",
        "sold_total_nums": "696",
        "sortnum": 1003,
        "notice": "剩1天",
        "is_remind": "0",
        "is_start": "1"
      },
      {
        "spec_id": "13457",
        "spec_name": "迪士尼玩具清仓专场",
        "banner": "http://s05.lmbang.com/M00/26/F2/DpgiA1hWvA-AZPmyAALVYE6TNU8755.jpg",
        "start_time": "1482285600",
        "end_time": "1482631199",
        "hits": "578",
        "remind_num": "0",
        "discount": "1.2",
        "typeid": "0",
        "ad_link": "",
        "sold_total_nums": "4248",
        "sortnum": 1002,
        "notice": "剩1天",
        "is_remind": "0",
        "is_start": "1"
      },
      {
        "spec_id": "13097",
        "spec_name": "Streamland/新溪岛品牌专场",
        "banner": "http://s06.lmbang.com/M00/02/41/ecloA1gkHUKAWW_VAAIdrHa2rm8676.jpg",
        "start_time": "1482458400",
        "end_time": "1482804000",
        "hits": "468",
        "remind_num": "2",
        "discount": "4.9",
        "typeid": "0",
        "ad_link": "",
        "sold_total_nums": "2364",
        "sortnum": 1000,
        "notice": "剩3天",
        "is_remind": "0",
        "is_start": "1"
      },
      {
        "spec_id": "13221",
        "spec_name": "圣元品牌专场",
        "banner": "http://s02.lmbang.com/M00/1E/E3/DpgiA1gyqeKAAgs0AAM0O-h3d68230.jpg",
        "start_time": "1482285600",
        "end_time": "1482631200",
        "hits": "573",
        "remind_num": "7",
        "discount": "8.7",
        "typeid": "0",
        "ad_link": "",
        "sold_total_nums": "439",
        "sortnum": 1000,
        "notice": "剩1天",
        "is_remind": "0",
        "is_start": "1"
      }
    ],
    "seckill": [],
    "top": []
  },
  "timestamp": 1482465584
}